libreria_ruggiero/__init__.py
libreria_ruggiero/calcolatrice.py
libreria_ruggiero-0.1.dist-info/LICENSE
libreria_ruggiero-0.1.dist-info/METADATA
libreria_ruggiero-0.1.dist-info/WHEEL
libreria_ruggiero-0.1.dist-info/top_level.txt
libreria_ruggiero-0.1.dist-info/RECORD
