Metadata-Version: 2.1
Name: libreria_ruggiero
Version: 0.1
Summary: Una libreria di esempio
Home-page: https://github.com
Author: MGDLab
Author-email: luca.santaniello.81@gmail.com
License: MIT
License-File: LICENSE
